sailing_log/__init__.py
sailing_log/logger.py
sailing_log-0.4.4.dist-info/LICENSE
sailing_log-0.4.4.dist-info/METADATA
sailing_log-0.4.4.dist-info/WHEEL
sailing_log-0.4.4.dist-info/top_level.txt
sailing_log-0.4.4.dist-info/RECORD
